{
  "dependencies": {
    "mssql1": {
      "serviceConnectorResourceId": "/subscriptions/[parameters('subscriptionId')]/resourceGroups/[parameters('resourceGroupName')]/providers/Microsoft.ServiceLinker/locations/eastus/connectors/ConnectionStringsDefaultConnection_8FB473E93E",
      "secretStore": null,
      "resourceId": "/subscriptions/[parameters('subscriptionId')]/resourceGroups/[parameters('resourceGroupName')]/providers/Microsoft.Sql/servers/kanbandbserver/databases/kanbandb",
      "type": "mssql.azure",
      "connectionId": "ConnectionStrings:DefaultConnection",
      "dynamicId": null
    }
  }
}